OtherProjects/Python/VHDL Parser/JK_FlipFlop.vhdl
library ieee;
use ieee.std_logic_1164.all;

entity JK_FlipFlop is 
port (
    j, k, clk: in std_logic;
	q, nq: out std_logic
);
end JK_FlipFlop;

architecture rtl of JK_FlipFlop is
    signal jk : std_logic_vector(1 downto 0);
    signal q_int : std_logic := '0';
begin
    jk <= j & k;
	process (clk)
        
    begin
        if rising_edge(clk) then
            case (jk) is
                when "00" =>
                    q_int <= q_int;

                when "01" =>
                    q_int <= '0';

                when "10" =>
                    q_int <= '1';

                when "11" =>
                    q_int <= not q_int;

                when others =>
                    q_int <= '0';
            end case;
        end if;
    end process;
    q <= q_int;
    nq <= not q_int;
end rtl;

Cpp/Extern/Digitaltechnik/_VHDL_/Aufgabe 2/JK_FlipFlop-test.vhdl
------------------------------------------------
-- THIS IS A TESTBENCH                        --
-- CREATOR:                                   --
-- OWNER:                                     --
------------------------------------------------
library ieee;
use ieee.std_logic_1164.all;

entity testbench_jk is
end testbench_jk;

architecture rtl of testbench_jk is

    signal clk  : std_logic := '0';
    signal j  : std_logic := '0';
    signal k  : std_logic := '0';
    signal out1 : std_logic;

begin

    port_inst: entity work.JK_FlipFlop
        port map (
            clk => clk,
            j => j,
            k => k,
            q => out1
        );

    tb: process
    begin
        for i in 1 to 2 loop

            clk <= '0'; j <= '0'; k <= '1'; wait for 250 ns;
            clk <= '1'; j <= '0'; k <= '0'; wait for 250 ns;
            clk <= '0'; j <= '1'; k <= '0'; wait for 250 ns;
            clk <= '1'; j <= '1'; k <= '1'; wait for 250 ns;

        end loop;

        wait;
    end process tb;

end rtl;

Cpp/Extern/Digitaltechnik/_VHDL_/Aufgabe 2/wave_jk.vcd
$date
  Mon May 11 11:49:22 2026
$end
$version
  GHDL v0
$end
$timescale
  1 fs
$end
$scope module standard $end
$upscope $end
$scope module std_logic_1164 $end
$upscope $end
$scope module testbench_jk $end
$var reg 1 ! clk $end
$var reg 1 " j $end
$var reg 1 # k $end
$var reg 1 $ out1 $end
$scope module port_inst $end
$var reg 1 % j $end
$var reg 1 & k $end
$var reg 1 ' clk $end
$var reg 1 ( q $end
$var reg 1 ) nq $end
$var reg 2 * jk[1:0] $end
$var reg 1 + q_int $end
$upscope $end
$upscope $end
$enddefinitions $end
#0
0!
0"
1#
0$
0%
1&
0'
0(
1)
b01 *
0+
#250000000
1!
0#
0&
1'
b00 *
#500000000
0!
1"
1%
0'
b10 *
#750000000
1!
1#
1$
1&
1'
1(
0)
b11 *
1+
#1000000000
0!
0"
0%
0'
b01 *
#1250000000
1!
0#
0$
0&
1'
0(
1)
b00 *
0+
#1500000000
0!
1"
1%
0'
b10 *
#1750000000
1!
1#
1$
1&
1'
1(
0)
b11 *
1+
