Cpp/Extern/Digitaltechnik/_VHDL_/Aufgabe 3/Counter.vhdl
library ieee;
use ieee.std_logic_1164.all;
use IEEE.NUMERIC_STD.all;

entity Counter is 
port (
    nClear, nLoad : in std_logic;
	d_intput : in std_logic_vector(3 downto 0);
    clk : in std_logic;
    p, t : in std_logic;
    
    q1,q2,q3,q4 : out std_logic;
    carry : out std_logic
);
end Counter;

architecture rtl of Counter is
    signal q_int : std_logic_vector(4 downto 0) := "00000";
begin

    process(clk, nLoad, nClear)
    begin
        if nLoad = '0' then
            q_int(3 downto 0) <= d_intput;
        elsif nClear = '0' then
            q_int <= "00000";
        end if;
        if rising_edge(clk) then
            if (p = '1' and t = '1') then
                q_int <= std_logic_vector(unsigned(q_int) + 1);
            end if;
        end if;
    end process;

    carry <= q_int(4);
    q1 <= q_int(0);
    q2 <= q_int(1);
    q3 <= q_int(2);
    q4 <= q_int(3);
    
end rtl;

Cpp/Extern/Digitaltechnik/_VHDL_/Aufgabe 3/Counter_tb.vhdl
library ieee;
use ieee.std_logic_1164.all;
entity Counter_tb is end;
architecture sim of Counter_tb is
    signal clk : std_logic := '0';
    signal nClear : std_logic := '0';
    signal nLoad : std_logic := '0';
    signal d_intput : std_logic_vector(3 downto 0) := (others => '0');
    signal p : std_logic := '0';
    signal t : std_logic := '0';
    signal q1 : std_logic := '0';
    signal q2 : std_logic := '0';
    signal q3 : std_logic := '0';
    signal q4 : std_logic := '0';
    signal carry : std_logic := '0';
begin
    port_inst: entity work.Counter
         port map (
            clk => clk,
            nClear => nClear,
            nLoad => nLoad,
            d_intput => d_intput,
            p => p,
            t => t,
            q1 => q1,
            q2 => q2,
            q3 => q3,
            q4 => q4,
            carry => carry
         );
    clk_proc: process
    begin
        for i in 0 to 30 loop
            clk <= '0'; wait for 125.0 ns;
            clk <= '1'; wait for 125.0 ns;
        end loop;
        wait;
    end process;

    tb: process
    begin
            p <= '1'; t <= '1'; nLoad <= '1'; nClear <= '1'; wait for 6000 ns;
            p <= '0'; t <= '0'; nLoad <= '0'; d_intput <= "1010"; wait for 2000 ns;
            p <= '0'; t <= '0'; nLoad <= '1'; nClear <= '0'; d_intput <= "1010"; wait for 2000 ns;

        wait;
    end process;
end architecture;

OtherProjects/VHDL/_VHDL_/Aufgabe 3/wave.vcd
$date
  Tue May 19 11:19:37 2026
$end
$version
  GHDL v0
$end
$timescale
  1 fs
$end
$scope module standard $end
$upscope $end
$scope module std_logic_1164 $end
$upscope $end
$scope module numeric_std $end
$upscope $end
$scope module counter_tb $end
$var reg 1 ! clk $end
$var reg 1 " nclear $end
$var reg 1 # nload $end
$var reg 4 $ d_intput[3:0] $end
$var reg 1 % p $end
$var reg 1 & t $end
$var reg 1 ' q1 $end
$var reg 1 ( q2 $end
$var reg 1 ) q3 $end
$var reg 1 * q4 $end
$var reg 1 + carry $end
$scope module port_inst $end
$var reg 1 , nclear $end
$var reg 1 - nload $end
$var reg 4 . d_intput[3:0] $end
$var reg 1 / clk $end
$var reg 1 0 p $end
$var reg 1 1 t $end
$var reg 1 2 q1 $end
$var reg 1 3 q2 $end
$var reg 1 4 q3 $end
$var reg 1 5 q4 $end
$var reg 1 6 carry $end
$var reg 5 7 q_int[4:0] $end
$upscope $end
$upscope $end
$enddefinitions $end
#0
0!
1"
1#
b0000 $
1%
1&
0'
0(
0)
0*
0+
1,
1-
b0000 .
0/
10
11
02
03
04
05
06
b00000 7
#125000000
1!
1'
1/
12
b00001 7
#250000000
0!
0/
#375000000
1!
0'
1(
1/
02
13
b00010 7
#500000000
0!
0/
#625000000
1!
1'
1/
12
b00011 7
#750000000
0!
0/
#875000000
1!
0'
0(
1)
1/
02
03
14
b00100 7
#1000000000
0!
0/
#1125000000
1!
1'
1/
12
b00101 7
#1250000000
0!
0/
#1375000000
1!
0'
1(
1/
02
13
b00110 7
#1500000000
0!
0/
#1625000000
1!
1'
1/
12
b00111 7
#1750000000
0!
0/
#1875000000
1!
0'
0(
0)
1*
1/
02
03
04
15
b01000 7
#2000000000
0!
0/
#2125000000
1!
1'
1/
12
b01001 7
#2250000000
0!
0/
#2375000000
1!
0'
1(
1/
02
13
b01010 7
#2500000000
0!
0/
#2625000000
1!
1'
1/
12
b01011 7
#2750000000
0!
0/
#2875000000
1!
0'
0(
1)
1/
02
03
14
b01100 7
#3000000000
0!
0/
#3125000000
1!
1'
1/
12
b01101 7
#3250000000
0!
0/
#3375000000
1!
0'
1(
1/
02
13
b01110 7
#3500000000
0!
0/
#3625000000
1!
1'
1/
12
b01111 7
#3750000000
0!
0/
#3875000000
1!
0'
0(
0)
0*
1+
1/
02
03
04
05
16
b10000 7
#4000000000
0!
0/
#4125000000
1!
1'
1/
12
b10001 7
#4250000000
0!
0/
#4375000000
1!
0'
1(
1/
02
13
b10010 7
#4500000000
0!
0/
#4625000000
1!
1'
1/
12
b10011 7
#4750000000
0!
0/
#4875000000
1!
0'
0(
1)
1/
02
03
14
b10100 7
#5000000000
0!
0/
#5125000000
1!
1'
1/
12
b10101 7
#5250000000
0!
0/
#5375000000
1!
0'
1(
1/
02
13
b10110 7
#5500000000
0!
0/
#5625000000
1!
1'
1/
12
b10111 7
#5750000000
0!
0/
#5875000000
1!
0'
0(
0)
1*
1/
02
03
04
15
b11000 7
#6000000000
0!
0#
b1010 $
0%
0&
1(
0-
b1010 .
0/
00
01
13
b11010 7
#6125000000
1!
1/
#6250000000
0!
0/
#6375000000
1!
1/
#6500000000
0!
0/
#6625000000
1!
1/
#6750000000
0!
0/
#6875000000
1!
1/
#7000000000
0!
0/
#7125000000
1!
1/
#7250000000
0!
0/
#7375000000
1!
1/
#7500000000
0!
0/
#7625000000
1!
1/
#8000000000
0"
1#
0(
0*
0+
0,
1-
03
05
06
b00000 7
