OtherProjects/VHDL/_VHDL_/Aufgabe 1/NOR_AND.vhdl
library ieee;
use ieee.std_logic_1164.all;

entity NOR_AND is 
port (
    a, b: in std_logic;
	q: out std_logic
);
end NOR_AND;

architecture rtl of NOR_AND is
begin
	q <= (a and b) or (a nor b);
end rtl;

Cpp/Extern/Digitaltechnik/_VHDL_/Aufgabe 1/NOR_AND-test.vhdl
------------------------------------------------
-- THIS IS A TESTBENCH                        --
-- CREATOR:                                   --
-- OWNER:                                     --
------------------------------------------------
library ieee;
use ieee.std_logic_1164.all;

entity testbench is
end testbench;

architecture rtl of testbench is

    signal in1  : std_logic := '0';
    signal in2  : std_logic := '0';
    signal out1 : std_logic;

begin

    port_inst: entity work.NOR_AND
        port map (
            a => in1,
            b => in2,
            q => out1
        );

    tb: process
    begin
        for i in 1 to 2 loop

            in1 <= '0'; in2 <= '0'; wait for 250 ns;
            in1 <= '1'; in2 <= '0'; wait for 250 ns;
            in1 <= '0'; in2 <= '1'; wait for 250 ns;
            in1 <= '1'; in2 <= '1'; wait for 250 ns;

        end loop;

        wait;
    end process tb;

end rtl;

Cpp/Extern/Digitaltechnik/_VHDL_/Aufgabe 1/wave.vcd
$date
  Sun May 10 16:01:01 2026
$end
$version
  GHDL v0
$end
$timescale
  1 fs
$end
$scope module standard $end
$upscope $end
$scope module std_logic_1164 $end
$upscope $end
$scope module testbench $end
$var reg 1 ! in1 $end
$var reg 1 " in2 $end
$var reg 1 # out1 $end
$scope module port_inst $end
$var reg 1 $ a $end
$var reg 1 % b $end
$var reg 1 & q $end
$upscope $end
$upscope $end
$enddefinitions $end
#0
0!
0"
1#
0$
0%
1&
#250000000
1!
0#
1$
0&
#500000000
0!
1"
0$
1%
#750000000
1!
1#
1$
1&
#1000000000
0!
0"
0$
0%
#1250000000
1!
0#
1$
0&
#1500000000
0!
1"
0$
1%
#1750000000
1!
1#
1$
1&
