OtherProjects/Python/VHDL Parser/JK_FlipFlop.vhdl
library ieee;
use ieee.std_logic_1164.all;

entity JK_FlipFlop is 
port (
    j, k, clk: in std_logic;
	q, nq: out std_logic
);
end JK_FlipFlop;

architecture rtl of JK_FlipFlop is
    signal jk : std_logic_vector(1 downto 0);
    signal q_int : std_logic := '0';
begin
    jk <= j & k;
	process (clk)
        
    begin
        if rising_edge(clk) then
            case (jk) is
                when "00" =>
                    q_int <= q_int;

                when "01" =>
                    q_int <= '0';

                when "10" =>
                    q_int <= '1';

                when "11" =>
                    q_int <= not q_int;

                when others =>
                    q_int <= '0';
            end case;
        end if;
    end process;
    q <= q_int;
    nq <= not q_int;
end rtl;

OtherProjects/Python/VHDL Parser/JK_FlipFlop_tb.vhdl
library ieee;
use ieee.std_logic_1164.all;
entity JK_FlipFlop_tb is end;
architecture sim of JK_FlipFlop_tb is
    signal clk : std_logic := '0';
    signal j : std_logic := '0';
    signal k : std_logic := '0';
    signal q : std_logic := '0';
    signal nq : std_logic := '0';
begin
    port_inst: entity work.JK_FlipFlop
         port map (
            clk => clk,
            j => j,
            k => k,
            q => q,
            nq => nq
         );
    clk_proc: process
    begin
        for i in 0 to 20 loop
            clk <= '0'; wait for 125.0 ns;
            clk <= '1'; wait for 125.0 ns;
        end loop;
        wait;
    end process;

    tb: process
    begin
        j <= '0';
        k <= '0';
       wait for 250 ns;
        j <= '0';
        k <= '1';
       wait for 250 ns;
        j <= '1';
        k <= '0';
       wait for 250 ns;
        j <= '1';
        k <= '1';
       wait for 250 ns;
        wait;
    end process;
end architecture;

OtherProjects/Python/VHDL Parser/wave.vcd
$date
  Tue May 19 09:43:01 2026
$end
$version
  GHDL v0
$end
$timescale
  1 fs
$end
$scope module standard $end
$upscope $end
$scope module std_logic_1164 $end
$upscope $end
$scope module jk_flipflop_tb $end
$var reg 1 ! clk $end
$var reg 1 " j $end
$var reg 1 # k $end
$var reg 1 $ q $end
$var reg 1 % nq $end
$scope module port_inst $end
$var reg 1 & j $end
$var reg 1 ' k $end
$var reg 1 ( clk $end
$var reg 1 ) q $end
$var reg 1 * nq $end
$var reg 2 + jk[1:0] $end
$var reg 1 , q_int $end
$upscope $end
$upscope $end
$enddefinitions $end
#0
0!
0"
0#
0$
1%
0&
0'
0(
0)
1*
b00 +
0,
#125000000
1!
1(
#250000000
0!
1#
1'
0(
b01 +
#375000000
1!
1(
#500000000
0!
1"
0#
1&
0'
0(
b10 +
#625000000
1!
1$
0%
1(
1)
0*
1,
#750000000
0!
1#
1'
0(
b11 +
#875000000
1!
0$
1%
1(
0)
1*
0,
#1000000000
0!
0(
#1125000000
1!
1$
0%
1(
1)
0*
1,
#1250000000
0!
0(
#1375000000
1!
0$
1%
1(
0)
1*
0,
#1500000000
0!
0(
#1625000000
1!
1$
0%
1(
1)
0*
1,
#1750000000
0!
0(
#1875000000
1!
0$
1%
1(
0)
1*
0,
#2000000000
0!
0(
#2125000000
1!
1$
0%
1(
1)
0*
1,
#2250000000
0!
0(
#2375000000
1!
0$
1%
1(
0)
1*
0,
#2500000000
0!
0(
#2625000000
1!
1$
0%
1(
1)
0*
1,
#2750000000
0!
0(
#2875000000
1!
0$
1%
1(
0)
1*
0,
#3000000000
0!
0(
#3125000000
1!
1$
0%
1(
1)
0*
1,
#3250000000
0!
0(
#3375000000
1!
0$
1%
1(
0)
1*
0,
#3500000000
0!
0(
#3625000000
1!
1$
0%
1(
1)
0*
1,
#3750000000
0!
0(
#3875000000
1!
0$
1%
1(
0)
1*
0,
#4000000000
0!
0(
#4125000000
1!
1$
0%
1(
1)
0*
1,
#4250000000
0!
0(
#4375000000
1!
0$
1%
1(
0)
1*
0,
#4500000000
0!
0(
#4625000000
1!
1$
0%
1(
1)
0*
1,
#4750000000
0!
0(
#4875000000
1!
0$
1%
1(
0)
1*
0,
#5000000000
0!
0(
#5125000000
1!
1$
0%
1(
1)
0*
1,
